nubium_utils/__init__.py
nubium_utils/custom_exceptions.py
nubium_utils/dict_manipulator.py
nubium_utils/dump_topic_configs.py
nubium_utils/general_utils.py
nubium_utils/hashing_utils.py
nubium_utils/custom_apps/__init__.py
nubium_utils/custom_apps/eloqua_retriever.py
nubium_utils/custom_apps/flask_receiver.py
nubium_utils/custom_apps/rest_bulk_switcher.py
nubium_utils/custom_apps/salesforce_retriever.py
nubium_utils/eloqua_utils/__init__.py
nubium_utils/eloqua_utils/timestamps.py
nubium_utils/fluvii_extensions/__init__.py
nubium_utils/fluvii_extensions/apps/__init__.py
nubium_utils/fluvii_extensions/apps/config.py
nubium_utils/fluvii_extensions/apps/nubium_app.py
nubium_utils/fluvii_extensions/apps/nubium_multi_msg_app.py
nubium_utils/fluvii_extensions/apps/nubium_table_app.py
nubium_utils/fluvii_extensions/apps/transactions/__init__.py
nubium_utils/fluvii_extensions/apps/transactions/transaction.py
nubium_utils/fluvii_extensions/components/__init__.py
nubium_utils/fluvii_extensions/components/auth/__init__.py
nubium_utils/fluvii_extensions/components/auth/config.py
nubium_utils/fluvii_extensions/components/consumer/__init__.py
nubium_utils/fluvii_extensions/components/consumer/config.py
nubium_utils/fluvii_extensions/components/consumer/consumer.py
nubium_utils/fluvii_extensions/components/consumer/consumer_factory.py
nubium_utils/fluvii_extensions/components/metrics/__init__.py
nubium_utils/fluvii_extensions/components/metrics/manager/__init__.py
nubium_utils/fluvii_extensions/components/metrics/manager/config.py
nubium_utils/fluvii_extensions/components/metrics/manager/metrics_manager.py
nubium_utils/fluvii_extensions/components/metrics/pusher/__init__.py
nubium_utils/fluvii_extensions/components/metrics/pusher/config.py
nubium_utils/fluvii_extensions/components/producer/__init__.py
nubium_utils/fluvii_extensions/components/producer/config.py
nubium_utils/fluvii_extensions/components/producer/producer_factory.py
nubium_utils-4.2.0.dist-info/METADATA
nubium_utils-4.2.0.dist-info/WHEEL
nubium_utils-4.2.0.dist-info/top_level.txt
nubium_utils-4.2.0.dist-info/RECORD
