Metadata-Version: 2.1
Name: nubium-utils
Version: 4.2.0
Summary: Some Kafka utility functions and patterns for the nubium project
Home-page: https://gitlab.corp.redhat.com/mkt-ops-de/nubium-utils.git
Author: Edward Brennan
Author-email: ebrennan@redhat.com
Classifier: Programming Language :: Python :: 3
Classifier: License :: OSI Approved :: MIT License
Classifier: Operating System :: OS Independent
Requires-Dist: fluvii (<1.2.0,>=1.1.0)
Requires-Dist: aiosfstream
Requires-Dist: dictdiffer
Requires-Dist: psutil
Requires-Dist: pydantic
Requires-Dist: python-box (<7)
Requires-Dist: python-dateutil
Requires-Dist: python-dotenv
Requires-Dist: python-eloqua-wrapper
Requires-Dist: pytz
Requires-Dist: requests
Requires-Dist: simple-salesforce
Provides-Extra: dev
Requires-Dist: fluvii (<1.2.0,>=1.1.0) ; extra == 'dev'
Requires-Dist: aiosfstream ; extra == 'dev'
Requires-Dist: dictdiffer ; extra == 'dev'
Requires-Dist: psutil ; extra == 'dev'
Requires-Dist: pydantic ; extra == 'dev'
Requires-Dist: python-box (<7) ; extra == 'dev'
Requires-Dist: python-dateutil ; extra == 'dev'
Requires-Dist: python-dotenv ; extra == 'dev'
Requires-Dist: python-eloqua-wrapper ; extra == 'dev'
Requires-Dist: pytz ; extra == 'dev'
Requires-Dist: requests ; extra == 'dev'
Requires-Dist: simple-salesforce ; extra == 'dev'
Requires-Dist: pip-tools ; extra == 'dev'
Requires-Dist: pytest ; extra == 'dev'
Requires-Dist: pytest-cov ; extra == 'dev'
Requires-Dist: time-machine ; extra == 'dev'
Requires-Dist: twine ; extra == 'dev'
